kaust/__init__.py
kaust/ansible/__init__.py
kaust/ansible/dyinv/__init__.py
kaust/ansible/dyinv/exclude_hosts.py
kaust/ansible/dyinv/openstackconnection.py
kaust/ansible/dyinv/scubaconnection.py
kaust/ansible/dyinv/smt_psw.py
kaust/ansible/dyinv/test_inv.py
kaust-0.0.3.dist-info/METADATA
kaust-0.0.3.dist-info/WHEEL
kaust-0.0.3.dist-info/top_level.txt
kaust-0.0.3.dist-info/RECORD
