Metadata-Version: 2.1
Name: kaust
Version: 0.0.3
Summary: Python client for KAUST
Home-page: https://gitlab.kaust.edu.sa/kaust-rc/kaust-py
Author: Antonio Arena
Author-email: antonio.arena@kaust.edu.sa
License: Apache License, Version 2.0
Platform: UNKNOWN
Classifier: Development Status :: 5 - Production/Stable
Classifier: License :: OSI Approved :: Apache Software License
Classifier: Intended Audience :: Developers
Classifier: Operating System :: OS Independent
Classifier: Programming Language :: Python
Classifier: Programming Language :: Python :: 3
Classifier: Programming Language :: Python :: 3.5
Classifier: Programming Language :: Python :: 3.6
Requires-Dist: Cython
Requires-Dist: pymssql
Requires-Dist: openstacksdk (>=0.19.0)
